Leavitt-1.0.2.data/scripts/leavitt
leavitt/__init__.py
leavitt/psearch_py3.py
leavitt/rrlfit.py
leavitt/sampler.py
leavitt/selftemplate.py
leavitt/templates.py
leavitt/timeseries.py
leavitt/tmpfit.py
leavitt/utils.py
leavitt/var.py
leavitt/__pycache__/psearch_py3.cpython-37.pyc
leavitt/__pycache__/rrlfit.cpython-37.pyc
leavitt/__pycache__/selftemplate.cpython-37.pyc
leavitt/__pycache__/tmpfit.cpython-37.pyc
leavitt/__pycache__/utils.cpython-37.pyc
leavitt/data/LaydenTemplates.txt
leavitt/data/SesarTemplates_g.txt
leavitt/data/SesarTemplates_i.txt
leavitt/data/SesarTemplates_r.txt
leavitt/data/SesarTemplates_u.txt
leavitt/data/SesarTemplates_z.txt
leavitt/data/TemplateIDs&Types.txt
leavitt/data/layden_templates.fits
Leavitt-1.0.2.dist-info/LICENSE
Leavitt-1.0.2.dist-info/METADATA
Leavitt-1.0.2.dist-info/WHEEL
Leavitt-1.0.2.dist-info/top_level.txt
Leavitt-1.0.2.dist-info/RECORD
